gielladetect/__init__.py
gielladetect/text_cat.py
gielladetect/util.py
gielladetect/lm/ara.lm
gielladetect/lm/ara.wm
gielladetect/lm/bxr.lm
gielladetect/lm/bxr.wm
gielladetect/lm/ckb.lm
gielladetect/lm/ckb.wm
gielladetect/lm/dan.lm
gielladetect/lm/dan.wm
gielladetect/lm/deu.lm
gielladetect/lm/deu.wm
gielladetect/lm/eng.lm
gielladetect/lm/eng.wm
gielladetect/lm/est.lm
gielladetect/lm/est.wm
gielladetect/lm/fao.lm
gielladetect/lm/fao.wm
gielladetect/lm/fas.lm
gielladetect/lm/fas.wm
gielladetect/lm/fin.lm
gielladetect/lm/fin.wm
gielladetect/lm/fit.lm
gielladetect/lm/fit.wm
gielladetect/lm/fkv.lm
gielladetect/lm/fkv.wm
gielladetect/lm/fra.lm
gielladetect/lm/fra.wm
gielladetect/lm/hbs.lm
gielladetect/lm/hbs.wm
gielladetect/lm/isl.lm
gielladetect/lm/isl.wm
gielladetect/lm/ita.lm
gielladetect/lm/ita.wm
gielladetect/lm/kal.lm
gielladetect/lm/kal.wm
gielladetect/lm/kmr.lm
gielladetect/lm/kmr.wm
gielladetect/lm/koi.lm
gielladetect/lm/koi.wm
gielladetect/lm/kpv.lm
gielladetect/lm/kpv.wm
gielladetect/lm/krl.lm
gielladetect/lm/krl.wm
gielladetect/lm/mdf.lm
gielladetect/lm/mdf.wm
gielladetect/lm/mhr.lm
gielladetect/lm/mhr.wm
gielladetect/lm/mns.lm
gielladetect/lm/mns.wm
gielladetect/lm/mrj.lm
gielladetect/lm/mrj.wm
gielladetect/lm/myv.lm
gielladetect/lm/myv.wm
gielladetect/lm/nno.lm
gielladetect/lm/nno.wm
gielladetect/lm/nob.lm
gielladetect/lm/nob.wm
gielladetect/lm/olo.lm
gielladetect/lm/olo.wm
gielladetect/lm/pol.lm
gielladetect/lm/pol.wm
gielladetect/lm/rmf.lm
gielladetect/lm/rmf.wm
gielladetect/lm/rmn.lm
gielladetect/lm/rmn.wm
gielladetect/lm/rmu.lm
gielladetect/lm/rmu.wm
gielladetect/lm/rmy-rka.lm
gielladetect/lm/rmy-rka.wm
gielladetect/lm/rmy-rlo.lm
gielladetect/lm/rmy-rlo.wm
gielladetect/lm/ron.lm
gielladetect/lm/ron.wm
gielladetect/lm/rus.lm
gielladetect/lm/rus.wm
gielladetect/lm/sma.lm
gielladetect/lm/sma.wm
gielladetect/lm/sme.lm
gielladetect/lm/sme.wm
gielladetect/lm/smj.lm
gielladetect/lm/smj.wm
gielladetect/lm/smn.lm
gielladetect/lm/smn.wm
gielladetect/lm/sms.lm
gielladetect-1.0.3.dist-info/LICENSE.txt
gielladetect-1.0.3.dist-info/METADATA
gielladetect-1.0.3.dist-info/WHEEL
gielladetect-1.0.3.dist-info/top_level.txt
gielladetect-1.0.3.dist-info/RECORD
