Metadata-Version: 2.1
Name: gielladetect
Version: 1.0.3
Summary: Language detection module based on the GiellaLT models, specifically aimed at minority and indigenous languages
License: GPLv3
Project-URL: repository, https://github.com/NationalLibraryOfNorway/gielladetect
Classifier: License :: OSI Approved :: GNU General Public License v3 (GPLv3)
License-File: LICENSE.txt
Requires-Dist: typing-extensions >=4.12
